Workbook

Sheet Assumptions
A1: Sidewalk Mosaic Project — Financial Model Assumptions
A2: Working nonprofit name: TBD (placeholder used: Sidewalk Stories LA)
A4: PROGRAM VOLUME
A5: Panels completed, Month 1 | B5: 2
A6: Panels completed, Month 12 (ramp target) | B6: 6
A7: Share of panels sponsored by a local business (%) | B7: 0.5
A8: Annual panel growth, Year 2 vs Year 1 (%) | B8: 0.4
A9: Annual panel growth, Year 3 vs Year 2 (%) | B9: 0.3
A11: COST PER PANEL (variable, one mosaic sidewalk panel)
A12: Concrete prep and structural repair (licensed crew) | B12: 900
A13: Mosaic materials (tile, grout, sealant, safety gear for kids) | B13: 1000
A14: Teaching artist / program lead stipend per panel | B14: 400
A15: City right-of-way permit, average | B15: 400
A16: Total variable cost per panel | B16: =SUM(B12:B15)
A18: FIXED MONTHLY OPERATING COSTS
A19: Bookkeeping / nonprofit admin | B19: 500
A20: General liability + program insurance | B20: 300
A21: App hosting / maintenance (Jason's build) | B21: 200
A22: Marketing and social content | B22: 200
A23: Part-time program coordinator (optional, set 0 if unpaid) | B23: 1500
A24: Total fixed cost per month | B24: =SUM(B19:B23)
A26: ONE-TIME YEAR 1 STARTUP COSTS
A27: 501(c)(3) formation, legal and filing fees | B27: 2000
A28: App development, cash cost (0 if Jason contributes as sweat equity) | B28: 0
A29: Branding and website | B29: 1500
A30: Total one-time startup cost | B30: =SUM(B27:B29)
A32: REVENUE ASSUMPTIONS
A33: Individual donations, Month 1 (monthly) | B33: 500
A34: Individual donations, Month 12 (monthly) | B34: 1500
A35: Sponsorship fee per sponsored panel | B35: 750
A36: Grant revenue, Quarter 2 (one time) | B36: 5000
A37: Grant revenue, Quarter 4 (one time) | B37: 7500
A38: Events / merchandise, per month starting Month 6 | B38: 300
A40: Note: Safe Sidewalks LA rebate (up to $10,000 per property, per city program rules as of early 2026) is a homeowner-facing reimbursement, not modeled as direct nonprofit revenue. If you formally partner with the city or with homeowners on qualifying panels, this is realistic upside not reflected below.
A42: Fixed operating cost inflation, per year | B42: 0.05

Sheet Monthly Proforma - Year 1
A1: Sidewalk Mosaic Project — Year 1 Monthly Proforma
B3: Month 1 | C3: Month 2 | D3: Month 3 | E3: Month 4 | F3: Month 5 | G3: Month 6 | H3: Month 7 | I3: Month 8 | J3: Month 9 | K3: Month 10 | L3: Month 11 | M3: Month 12 | N3: Year 1 Total
A4: PROGRAM VOLUME
A5: Panels completed this month | B5: =Assumptions!$B$5+(Assumptions!$B$6-Assumptions!$B$5)/11*(1-1) | C5: =Assumptions!$B$5+(Assumptions!$B$6-Assumptions!$B$5)/11*(2-1) | D5: =Assumptions!$B$5+(Assumptions!$B$6-Assumptions!$B$5)/11*(3-1) | E5: =Assumptions!$B$5+(Assumptions!$B$6-Assumptions!$B$5)/11*(4-1) | F5: =Assumptions!$B$5+(Assumptions!$B$6-Assumptions!$B$5)/11*(5-1) | G5: =Assumptions!$B$5+(Assumptions!$B$6-Assumptions!$B$5)/11*(6-1) | H5: =Assumptions!$B$5+(Assumptions!$B$6-Assumptions!$B$5)/11*(7-1) | I5: =Assumptions!$B$5+(Assumptions!$B$6-Assumptions!$B$5)/11*(8-1) | J5: =Assumptions!$B$5+(Assumptions!$B$6-Assumptions!$B$5)/11*(9-1) | K5: =Assumptions!$B$5+(Assumptions!$B$6-Assumptions!$B$5)/11*(10-1) | L5: =Assumptions!$B$5+(Assumptions!$B$6-Assumptions!$B$5)/11*(11-1) | M5: =Assumptions!$B$5+(Assumptions!$B$6-Assumptions!$B$5)/11*(12-1) | N5: =SUM(B5:M5)
A6: Of which, sponsored panels | B6: =B5*Assumptions!$B$7 | C6: =C5*Assumptions!$B$7 | D6: =D5*Assumptions!$B$7 | E6: =E5*Assumptions!$B$7 | F6: =F5*Assumptions!$B$7 | G6: =G5*Assumptions!$B$7 | H6: =H5*Assumptions!$B$7 | I6: =I5*Assumptions!$B$7 | ... M6: =M5*Assumptions!$B$7 | N6: =SUM(B6:M6)
A8: REVENUE
A9: Individual donations | B9: =Assumptions!$B$33+(Assumptions!$B$34-Assumptions!$B$33)/11*(1-1) | C9: =Assumptions!$B$33+(Assumptions!$B$34-Assumptions!$B$33)/11*(2-1) | D9: =Assumptions!$B$33+(Assumptions!$B$34-Assumptions!$B$33)/11*(3-1) | E9: =Assumptions!$B$33+(Assumptions!$B$34-Assumptions!$B$33)/11*(4-1) | F9: =Assumptions!$B$33+(Assumptions!$B$34-Assumptions!$B$33)/11*(5-1) | G9: =Assumptions!$B$33+(Assumptions!$B$34-Assumptions!$B$33)/11*(6-1) | H9: =Assumptions!$B$33+(Assumptions!$B$34-Assumptions!$B$33)/11*(7-1) | I9: =Assumptions!$B$33+(Assumptions!$B$34-Assumptions!$B$33)/11*(8-1) | J9: =Assumptions!$B$33+(Assumptions!$B$34-Assumptions!$B$33)/11*(9-1) | K9: =Assumptions!$B$33+(Assumptions!$B$34-Assumptions!$B$33)/11*(10-1) | L9: =Assumptions!$B$33+(Assumptions!$B$34-Assumptions!$B$33)/11*(11-1) | M9: =Assumptions!$B$33+(Assumptions!$B$34-Assumptions!$B$33)/11*(12-1) | N9: =SUM(B9:M9)
A10: Sponsorship revenue | B10: =B6*Assumptions!$B$35 | C10: =C6*Assumptions!$B$35 | D10: =D6*Assumptions!$B$35 | E10: =E6*Assumptions!$B$35 | F10: =F6*Assumptions!$B$35 | G10: =G6*Assumptions!$B$35 | H10: =H6*Assumptions!$B$35 | I10: =I6*Assumptions!$B$35 | ... M10: =M6*Assumptions!$B$35 | N10: =SUM(B10:M10)
A11: Grant revenue | B11: 0 | C11: 0 | D11: 0 | E11: 0 | F11: 0 | G11: =Assumptions!$B$36 | H11: 0 | I11: 0 | J11: 0 | K11: 0 | L11: 0 | M11: =Assumptions!$B$37 | N11: =SUM(B11:M11)
A12: Events / merchandise (from Month 6) | B12: 0 | C12: 0 | D12: 0 | E12: 0 | F12: 0 | G12: =Assumptions!$B$38 | H12: =Assumptions!$B$38 | I12: =Assumptions!$B$38 | J12: =Assumptions!$B$38 | K12: =Assumptions!$B$38 | L12: =Assumptions!$B$38 | M12: =Assumptions!$B$38 | N12: =SUM(B12:M12)
A13: Total revenue | B13: =SUM(B9:B12) | C13: =SUM(C9:C12) | D13: =SUM(D9:D12) | E13: =SUM(E9:E12) | F13: =SUM(F9:F12) | G13: =SUM(G9:G12) | H13: =SUM(H9:H12) | I13: =SUM(I9:I12) | ... M13: =SUM(M9:M12) | N13: =SUM(B13:M13)
A15: COSTS
A16: Panel variable cost (concrete, materials, artist, permit) | B16: =B5*Assumptions!$B$16 | C16: =C5*Assumptions!$B$16 | D16: =D5*Assumptions!$B$16 | E16: =E5*Assumptions!$B$16 | F16: =F5*Assumptions!$B$16 | G16: =G5*Assumptions!$B$16 | H16: =H5*Assumptions!$B$16 | I16: =I5*Assumptions!$B$16 | ... M16: =M5*Assumptions!$B$16 | N16: =SUM(B16:M16)
A17: Fixed operating cost | B17: =Assumptions!$B$24 | C17: =Assumptions!$B$24 | D17: =Assumptions!$B$24 | E17: =Assumptions!$B$24 | F17: =Assumptions!$B$24 | G17: =Assumptions!$B$24 | H17: =Assumptions!$B$24 | I17: =Assumptions!$B$24 | ... M17: =Assumptions!$B$24 | N17: =SUM(B17:M17)
A18: One-time startup cost (Month 1 only) | B18: =Assumptions!$B$30 | C18: 0 | D18: 0 | E18: 0 | F18: 0 | G18: 0 | H18: 0 | I18: 0 | J18: 0 | K18: 0 | L18: 0 | M18: 0 | N18: =SUM(B18:M18)
A19: Total costs | B19: =SUM(B16:B18) | C19: =SUM(C16:C18) | D19: =SUM(D16:D18) | E19: =SUM(E16:E18) | F19: =SUM(F16:F18) | G19: =SUM(G16:G18) | H19: =SUM(H16:H18) | I19: =SUM(I16:I18) | ... M19: =SUM(M16:M18) | N19: =SUM(B19:M19)
A21: NET
A22: Net monthly cash flow | B22: =B13-B19 | C22: =C13-C19 | D22: =D13-D19 | E22: =E13-E19 | F22: =F13-F19 | G22: =G13-G19 | H22: =H13-H19 | I22: =I13-I19 | ... M22: =M13-M19 | N22: =SUM(B22:M22)
A23: Cumulative cash position | B23: =B22 | C23: =B23+C22 | D23: =C23+D22 | E23: =D23+E22 | F23: =E23+F22 | G23: =F23+G22 | H23: =G23+H22 | I23: =H23+I22 | J23: =I23+J22 | ... M23: =L23+M22
A25: All month columns pull from the Assumptions tab. Change any blue/yellow cell there and this proforma recalculates.

Sheet Annual Summary Y1-Y3
A1: Sidewalk Mosaic Project — 3-Year Annual Summary
B3: Year 1 | C3: Year 2 | D3: Year 3
A4: PROGRAM VOLUME
A5: Total panels completed | B5: ='Monthly Proforma - Year 1'!N5 | C5: =B5*(1+Assumptions!$B$8) | D5: =C5*(1+Assumptions!$B$9)
A7: REVENUE AND COSTS
A8: Total revenue | B8: ='Monthly Proforma - Year 1'!N13 | C8: =B8*(1+Assumptions!$B$8) | D8: =C8*(1+Assumptions!$B$9)
A9: Variable panel costs | B9: ='Monthly Proforma - Year 1'!N16 | C9: =B9*(1+Assumptions!$B$8) | D9: =C9*(1+Assumptions!$B$9)
A10: Fixed operating costs | B10: ='Monthly Proforma - Year 1'!N17 | C10: =B10*(1+Assumptions!$B$42) | D10: =C10*(1+Assumptions!$B$42)
A11: One-time startup costs | B11: ='Monthly Proforma - Year 1'!N18 | C11: 0 | D11: 0
A12: Total costs | B12: =SUM(B9:B11) | C12: =SUM(C9:C11) | D12: =SUM(D9:D11)
A14: NET
A15: Net income | B15: =B8-B12 | C15: =C8-C12 | D15: =D8-D12
A16: Cumulative cash position | B16: =B15 | C16: =B16+C15 | D16: =C16+D15
A18: Year 1 pulls directly from the monthly tab. Years 2 and 3 are simplified: revenue and variable costs scale with panel growth, fixed costs grow by the inflation assumption. Adjust growth and inflation assumptions on the Assumptions tab.

Sheet Pilot Scenario - Year 1
A1: Sidewalk Stories LA — Pilot Scenario Year 1 (10 Panels)
B3: Month 1 | C3: Month 2 | D3: Month 3 | E3: Month 4 | F3: Month 5 | G3: Month 6 | H3: Month 7 | I3: Month 8 | J3: Month 9 | K3: Month 10 | L3: Month 11 | M3: Month 12 | N3: Year 1 Total
A4: PROGRAM VOLUME
A5: Panels completed this month | B5: 1 | C5: 1 | D5: 1 | E5: 1 | F5: 1 | G5: 1 | H5: 1 | I5: 1 | J5: 1 | K5: 1 | L5: 0 | M5: 0 | N5: =SUM(B5:M5)
A6: Of which, sponsored panels (50%) | B6: 0.5 | C6: 0.5 | D6: 0.5 | E6: 0.5 | F6: 0.5 | G6: 0.5 | H6: 0.5 | I6: 0.5 | J6: 0.5 | K6: 0.5 | L6: 0 | M6: 0 | N6: =SUM(B6:M6)
A8: REVENUE
A9: Individual donations | B9: 250 | C9: 300 | D9: 350 | E9: 400 | F9: 450 | G9: 500 | H9: 550 | I9: 600 | J9: 650 | K9: 700 | L9: 750 | M9: 750 | N9: =SUM(B9:M9)
A10: Sponsorship revenue ($750/panel) | B10: 375 | C10: 375 | D10: 375 | E10: 375 | F10: 375 | G10: 375 | H10: 375 | I10: 375 | J10: 375 | K10: 375 | L10: 0 | M10: 0 | N10: =SUM(B10:M10)
A11: Grant revenue | B11: 0 | C11: 0 | D11: 0 | E11: 5000 | F11: 0 | G11: 0 | H11: 0 | I11: 0 | J11: 0 | K11: 0 | L11: 0 | M11: 10000 | N11: =SUM(B11:M11)
A12: Events / merchandise | B12: 0 | C12: 0 | D12: 0 | E12: 0 | F12: 0 | G12: 250 | H12: 250 | I12: 250 | J12: 250 | K12: 250 | L12: 250 | M12: 250 | N12: =SUM(B12:M12)
A13: Total revenue | B13: =SUM(B9:B12) | C13: =SUM(C9:C12) | D13: =SUM(D9:D12) | E13: =SUM(E9:E12) | F13: =SUM(F9:F12) | G13: =SUM(G9:G12) | H13: =SUM(H9:H12) | I13: =SUM(I9:I12) | ... N13: =SUM(N9:N12)
A15: COSTS
A16: Panel variable cost ($2,700/panel) | B16: 2700 | C16: 2700 | D16: 2700 | E16: 2700 | F16: 2700 | G16: 2700 | H16: 2700 | I16: 2700 | J16: 2700 | K16: 2700 | L16: 0 | M16: 0 | N16: =SUM(B16:M16)
A17: Fixed operating cost | B17: 850 | C17: 850 | D17: 850 | E17: 850 | F17: 850 | G17: 850 | H17: 850 | I17: 850 | J17: 850 | K17: 850 | L17: 850 | M17: 850 | N17: =SUM(B17:M17)
A18: One-time startup cost (Month 1 only) | B18: 1500 | C18: 0 | D18: 0 | E18: 0 | F18: 0 | G18: 0 | H18: 0 | I18: 0 | J18: 0 | K18: 0 | L18: 0 | M18: 0 | N18: =SUM(B18:M18)
A19: Total costs | B19: =B16+B17+B18 | C19: =C16+C17+C18 | D19: =D16+D17+D18 | E19: =E16+E17+E18 | F19: =F16+F17+F18 | G19: =G16+G17+G18 | H19: =H16+H17+H18 | I19: =I16+I17+I18 | ... N19: =N16+N17+N18
A21: NET
A22: Net monthly cash flow | B22: =B13-B19 | C22: =C13-C19 | D22: =D13-D19 | E22: =E13-E19 | F22: =F13-F19 | G22: =G13-G19 | H22: =H13-H19 | I22: =I13-I19 | ... N22: =N13-N19
A23: Cumulative cash position | B23: =B22 | C23: =B23+C22 | D23: =C23+D22 | E23: =D23+E22 | F23: =E23+F22 | G23: =F23+G22 | H23: =G23+H22 | I23: =H23+I22 | J23: =I23+J22 | ... N23: =M23+N22
A25: Notes:
A26: This pilot scenario replaces the original 48-panel Year 1 plan. Program ramps to 10 panels across 10 months.
A27: Fixed costs reduced by eliminating the part-time coordinator and trimming admin/marketing budgets.
A28: Startup costs reduced to $1,500 (self-filed 501(c)(3), DIY branding).
A29: Grant revenue assumes one $5K Q2 community arts grant and one $10K Q4 youth development grant.

Sheet Grant Detail
A1: Sidewalk Stories LA — Grant Detail & Pipeline
A3: Funder | B3: Tier | C3: Focus Area | D3: Typical Award | E3: Target Ask | F3: Deadline | G3: Status | H3: Probability | I3: Notes
A4: Awesome Foundation LA | B4: 1 | C4: Community projects | D4: $1,000 | E4: $1,000 | F4: Rolling (monthly) | G4: Not yet applied | H4: High | I4: No 501(c)(3) required. Great for first panel materials.
A5: Neighborhood Council Grant | B5: 1 | C5: Local improvement | D5: $2,500 | E5: $2,500 | F5: Varies by council | G5: Not yet applied | H5: High | I5: Need pilot neighborhood selected.
A6: Local Business Sponsors (5) | B6: 4 | C6: Corporate sponsorship | D6: $750/panel | E6: $3,750 | F6: Ongoing | G6: Not yet approached | H6: High | I6: Logo on mosaic, social content, press mention.
A7: AARP Community Challenge | B7: 3 | C7: Livability / seniors | D7: $10,000 | E7: $10,000 | F7: Annual cycle (opens early year) | G7: Not yet applied | H7: Medium | I7: Strong fit: sidewalk safety for seniors.
A8: LA County Arts Commission | B8: 1 | C8: Public art / youth arts | D8: $10,000 | E8: $10,000 | F8: Check quarterly cycles | G8: Not yet applied | H8: Medium | I8: Directly funds public art in neighborhoods.
A9: City of LA DCA | B9: 1 | C9: Public art / youth | D9: $10,000 | E9: $10,000 | F9: Check annual cycle | G9: Not yet applied | H9: Medium | I9: DCA funds public art in the right of way.
A10: California Community Foundation | B10: 1 | C10: Arts / civic engagement | D10: $15,000 | E10: $15,000 | F10: Responsive grants (quarterly) | G10: Not yet applied | H10: Medium | I10: CCF funds LA County neighborhood improvement.
A11: Weingart Foundation | B11: 1 | C11: Youth / community | D11: $25,000 | E11: $25,000 | F11: Check guidelines | G11: Not yet applied | H11: Medium | I11: Explicitly funds programs improving neighborhoods for youth.
A12: National Endowment for the Arts | B12: 2 | C12: Public art / community | D12: $10,000 | E12: $15,000 | F12: Annual cycle | G12: Not yet applied | H12: Low-Medium | I12: Requires 501(c)(3) status or fiscal sponsor.
A13: Surdna Foundation | B13: 2 | C13: Creative placemaking | D13: $25,000 | E13: $25,000 | F13: Check guidelines | G13: Not yet applied | H13: Low-Medium | I13: Funds youth shaping built environment.
A14: Jewish Federation of Greater LA | B14: 4 | C14: Jewish community / youth | D14: $10,000 | E14: $10,000 | F14: Check annual cycle | G14: Not yet applied | H14: Medium | I14: If Jewish youth participate, strong fit.
A15: Safe Sidewalks LA Rebate | B15: 3 | C15: Cost offset / homeowner | D15: $10,000 | E15: $10,000 | F15: Ongoing | G15: Researching | H15: Medium | I15: Homeowner rebate, not direct nonprofit revenue.
A18: Pipeline Summary
A19: Total Year 1 Grant + Sponsor Target: | B19: =SUM(E4:E15)
A20: Less Conservative Estimate (60% of target): | B20: =B19*0.6
